<?xml version="1.0" encoding="UTF-8"?>

<!-- generated on Fri Oct 25 10:37:26 2019 by Eclipse SUMO Version 1.3.1
<configuration xmlns:xsi="http://www.w3.org/2001/XMLSchema-instance" xsi:noNamespaceSchemaLocation="http://sumo.dlr.de/xsd/sumoConfiguration.xsd">

    <input>
        <net-file value="corridor\corridor500.net.xml"/>
        <route-files value="corridor\corridor.flow.xml"/>
        <additional-files value="corridor\vtypes.add.xml"/>
    </input>

    <output>
        <tripinfo-output value="walabi_corridor\tripinfos49_routedist2.xml"/>
    </output>

    <report>
        <verbose value="true"/>
        <log value="corridor\log"/>
        <duration-log.statistics value="true"/>
        <no-step-log value="true"/>
    </report>

    <traci_server>
        <remote-port value="52536"/>
    </traci_server>

    <random_number>
        <random value="true"/>
    </random_number>

</configuration>
-->

<tlsStates xmlns:xsi="http://www.w3.org/2001/XMLSchema-instance" xsi:noNamespaceSchemaLocation="http://sumo.dlr.de/xsd/tlsstates_file.xsd">
    <tlsState time="0.00" id="gneJ10" programID="0" phase="0" state="GGgrrrGGgrrr"/>
    <tlsState time="0.00" id="gneJ11" programID="0" phase="2" state="rrrGGgrrrGGg"/>
    <tlsState time="0.00" id="gneJ12" programID="0" phase="0" state="GGgrrrGGgrrr"/>
    <tlsState time="24.00" id="gneJ12" programID="0" phase="1" state="yyyrrryyyrrr"/>
    <tlsState time="27.00" id="gneJ12" programID="0" phase="2" state="rrrGGgrrrGGg"/>
    <tlsState time="33.00" id="gneJ11" programID="0" phase="3" state="rrryyyrrryyy"/>
    <tlsState time="36.00" id="gneJ11" programID="0" phase="0" state="GGgrrrGGgrrr"/>
    <tlsState time="42.00" id="gneJ10" programID="0" phase="1" state="yyyrrryyyrrr"/>
    <tlsState time="45.00" id="gneJ10" programID="0" phase="2" state="rrrGGgrrrGGg"/>
    <tlsState time="69.00" id="gneJ12" programID="0" phase="3" state="rrryyyrrryyy"/>
    <tlsState time="72.00" id="gneJ12" programID="0" phase="0" state="GGgrrrGGgrrr"/>
    <tlsState time="78.00" id="gneJ11" programID="0" phase="1" state="yyyrrryyyrrr"/>
    <tlsState time="81.00" id="gneJ11" programID="0" phase="2" state="rrrGGgrrrGGg"/>
    <tlsState time="87.00" id="gneJ10" programID="0" phase="3" state="rrryyyrrryyy"/>
    <tlsState time="90.00" id="gneJ10" programID="0" phase="0" state="GGgrrrGGgrrr"/>
    <tlsState time="114.00" id="gneJ12" programID="0" phase="1" state="yyyrrryyyrrr"/>
    <tlsState time="117.00" id="gneJ12" programID="0" phase="2" state="rrrGGgrrrGGg"/>
    <tlsState time="123.00" id="gneJ11" programID="0" phase="3" state="rrryyyrrryyy"/>
    <tlsState time="126.00" id="gneJ11" programID="0" phase="0" state="GGgrrrGGgrrr"/>
    <tlsState time="132.00" id="gneJ10" programID="0" phase="1" state="yyyrrryyyrrr"/>
    <tlsState time="135.00" id="gneJ10" programID="0" phase="2" state="rrrGGgrrrGGg"/>
    <tlsState time="159.00" id="gneJ12" programID="0" phase="3" state="rrryyyrrryyy"/>
    <tlsState time="162.00" id="gneJ12" programID="0" phase="0" state="GGgrrrGGgrrr"/>
    <tlsState time="168.00" id="gneJ11" programID="0" phase="1" state="yyyrrryyyrrr"/>
    <tlsState time="171.00" id="gneJ11" programID="0" phase="2" state="rrrGGgrrrGGg"/>
    <tlsState time="177.00" id="gneJ10" programID="0" phase="3" state="rrryyyrrryyy"/>
    <tlsState time="180.00" id="gneJ10" programID="0" phase="0" state="GGgrrrGGgrrr"/>
    <tlsState time="204.00" id="gneJ12" programID="0" phase="1" state="yyyrrryyyrrr"/>
    <tlsState time="207.00" id="gneJ12" programID="0" phase="2" state="rrrGGgrrrGGg"/>
    <tlsState time="213.00" id="gneJ11" programID="0" phase="3" state="rrryyyrrryyy"/>
    <tlsState time="216.00" id="gneJ11" programID="0" phase="0" state="GGgrrrGGgrrr"/>
    <tlsState time="222.00" id="gneJ10" programID="0" phase="1" state="yyyrrryyyrrr"/>
    <tlsState time="225.00" id="gneJ10" programID="0" phase="2" state="rrrGGgrrrGGg"/>
    <tlsState time="249.00" id="gneJ12" programID="0" phase="3" state="rrryyyrrryyy"/>
    <tlsState time="252.00" id="gneJ12" programID="0" phase="0" state="GGgrrrGGgrrr"/>
    <tlsState time="258.00" id="gneJ11" programID="0" phase="1" state="yyyrrryyyrrr"/>
    <tlsState time="261.00" id="gneJ11" programID="0" phase="2" state="rrrGGgrrrGGg"/>
    <tlsState time="267.00" id="gneJ10" programID="0" phase="3" state="rrryyyrrryyy"/>
    <tlsState time="270.00" id="gneJ10" programID="0" phase="0" state="GGgrrrGGgrrr"/>
    <tlsState time="294.00" id="gneJ12" programID="0" phase="1" state="yyyrrryyyrrr"/>
    <tlsState time="297.00" id="gneJ12" programID="0" phase="2" state="rrrGGgrrrGGg"/>
    <tlsState time="303.00" id="gneJ11" programID="0" phase="3" state="rrryyyrrryyy"/>
    <tlsState time="306.00" id="gneJ11" programID="0" phase="0" state="GGgrrrGGgrrr"/>
    <tlsState time="312.00" id="gneJ10" programID="0" phase="1" state="yyyrrryyyrrr"/>
    <tlsState time="315.00" id="gneJ10" programID="0" phase="2" state="rrrGGgrrrGGg"/>
    <tlsState time="339.00" id="gneJ12" programID="0" phase="3" state="rrryyyrrryyy"/>
    <tlsState time="342.00" id="gneJ12" programID="0" phase="0" state="GGgrrrGGgrrr"/>
    <tlsState time="348.00" id="gneJ11" programID="0" phase="1" state="yyyrrryyyrrr"/>
    <tlsState time="351.00" id="gneJ11" programID="0" phase="2" state="rrrGGgrrrGGg"/>
    <tlsState time="357.00" id="gneJ10" programID="0" phase="3" state="rrryyyrrryyy"/>
    <tlsState time="360.00" id="gneJ10" programID="0" phase="0" state="GGgrrrGGgrrr"/>
    <tlsState time="384.00" id="gneJ12" programID="0" phase="1" state="yyyrrryyyrrr"/>
    <tlsState time="387.00" id="gneJ12" programID="0" phase="2" state="rrrGGgrrrGGg"/>
    <tlsState time="393.00" id="gneJ11" programID="0" phase="3" state="rrryyyrrryyy"/>
    <tlsState time="396.00" id="gneJ11" programID="0" phase="0" state="GGgrrrGGgrrr"/>
    <tlsState time="402.00" id="gneJ10" programID="0" phase="1" state="yyyrrryyyrrr"/>
    <tlsState time="405.00" id="gneJ10" programID="0" phase="2" state="rrrGGgrrrGGg"/>
    <tlsState time="429.00" id="gneJ12" programID="0" phase="3" state="rrryyyrrryyy"/>
    <tlsState time="432.00" id="gneJ12" programID="0" phase="0" state="GGgrrrGGgrrr"/>
    <tlsState time="438.00" id="gneJ11" programID="0" phase="1" state="yyyrrryyyrrr"/>
    <tlsState time="441.00" id="gneJ11" programID="0" phase="2" state="rrrGGgrrrGGg"/>
    <tlsState time="447.00" id="gneJ10" programID="0" phase="3" state="rrryyyrrryyy"/>
    <tlsState time="450.00" id="gneJ10" programID="0" phase="0" state="GGgrrrGGgrrr"/>
    <tlsState time="474.00" id="gneJ12" programID="0" phase="1" state="yyyrrryyyrrr"/>
    <tlsState time="477.00" id="gneJ12" programID="0" phase="2" state="rrrGGgrrrGGg"/>
    <tlsState time="483.00" id="gneJ11" programID="0" phase="3" state="rrryyyrrryyy"/>
    <tlsState time="486.00" id="gneJ11" programID="0" phase="0" state="GGgrrrGGgrrr"/>
    <tlsState time="492.00" id="gneJ10" programID="0" phase="1" state="yyyrrryyyrrr"/>
    <tlsState time="495.00" id="gneJ10" programID="0" phase="2" state="rrrGGgrrrGGg"/>
    <tlsState time="519.00" id="gneJ12" programID="0" phase="3" state="rrryyyrrryyy"/>
    <tlsState time="522.00" id="gneJ12" programID="0" phase="0" state="GGgrrrGGgrrr"/>
    <tlsState time="528.00" id="gneJ11" programID="0" phase="1" state="yyyrrryyyrrr"/>
    <tlsState time="531.00" id="gneJ11" programID="0" phase="2" state="rrrGGgrrrGGg"/>
    <tlsState time="537.00" id="gneJ10" programID="0" phase="3" state="rrryyyrrryyy"/>
    <tlsState time="540.00" id="gneJ10" programID="0" phase="0" state="GGgrrrGGgrrr"/>
    <tlsState time="564.00" id="gneJ12" programID="0" phase="1" state="yyyrrryyyrrr"/>
    <tlsState time="567.00" id="gneJ12" programID="0" phase="2" state="rrrGGgrrrGGg"/>
    <tlsState time="573.00" id="gneJ11" programID="0" phase="3" state="rrryyyrrryyy"/>
    <tlsState time="576.00" id="gneJ11" programID="0" phase="0" state="GGgrrrGGgrrr"/>
    <tlsState time="582.00" id="gneJ10" programID="0" phase="1" state="yyyrrryyyrrr"/>
    <tlsState time="585.00" id="gneJ10" programID="0" phase="2" state="rrrGGgrrrGGg"/>
    <tlsState time="609.00" id="gneJ12" programID="0" phase="3" state="rrryyyrrryyy"/>
    <tlsState time="612.00" id="gneJ12" programID="0" phase="0" state="GGgrrrGGgrrr"/>
    <tlsState time="618.00" id="gneJ11" programID="0" phase="1" state="yyyrrryyyrrr"/>
    <tlsState time="621.00" id="gneJ11" programID="0" phase="2" state="rrrGGgrrrGGg"/>
    <tlsState time="627.00" id="gneJ10" programID="0" phase="3" state="rrryyyrrryyy"/>
    <tlsState time="630.00" id="gneJ10" programID="0" phase="0" state="GGgrrrGGgrrr"/>
    <tlsState time="654.00" id="gneJ12" programID="0" phase="1" state="yyyrrryyyrrr"/>
    <tlsState time="657.00" id="gneJ12" programID="0" phase="2" state="rrrGGgrrrGGg"/>
    <tlsState time="663.00" id="gneJ11" programID="0" phase="3" state="rrryyyrrryyy"/>
    <tlsState time="666.00" id="gneJ11" programID="0" phase="0" state="GGgrrrGGgrrr"/>
    <tlsState time="672.00" id="gneJ10" programID="0" phase="1" state="yyyrrryyyrrr"/>
    <tlsState time="675.00" id="gneJ10" programID="0" phase="2" state="rrrGGgrrrGGg"/>
    <tlsState time="699.00" id="gneJ12" programID="0" phase="3" state="rrryyyrrryyy"/>
    <tlsState time="702.00" id="gneJ12" programID="0" phase="0" state="GGgrrrGGgrrr"/>
    <tlsState time="708.00" id="gneJ11" programID="0" phase="1" state="yyyrrryyyrrr"/>
    <tlsState time="711.00" id="gneJ11" programID="0" phase="2" state="rrrGGgrrrGGg"/>
    <tlsState time="717.00" id="gneJ10" programID="0" phase="3" state="rrryyyrrryyy"/>
    <tlsState time="720.00" id="gneJ10" programID="0" phase="0" state="GGgrrrGGgrrr"/>
    <tlsState time="744.00" id="gneJ12" programID="0" phase="1" state="yyyrrryyyrrr"/>
    <tlsState time="747.00" id="gneJ12" programID="0" phase="2" state="rrrGGgrrrGGg"/>
    <tlsState time="753.00" id="gneJ11" programID="0" phase="3" state="rrryyyrrryyy"/>
    <tlsState time="756.00" id="gneJ11" programID="0" phase="0" state="GGgrrrGGgrrr"/>
    <tlsState time="762.00" id="gneJ10" programID="0" phase="1" state="yyyrrryyyrrr"/>
    <tlsState time="765.00" id="gneJ10" programID="0" phase="2" state="rrrGGgrrrGGg"/>
    <tlsState time="789.00" id="gneJ12" programID="0" phase="3" state="rrryyyrrryyy"/>
    <tlsState time="792.00" id="gneJ12" programID="0" phase="0" state="GGgrrrGGgrrr"/>
    <tlsState time="798.00" id="gneJ11" programID="0" phase="1" state="yyyrrryyyrrr"/>
    <tlsState time="801.00" id="gneJ11" programID="0" phase="2" state="rrrGGgrrrGGg"/>
    <tlsState time="807.00" id="gneJ10" programID="0" phase="3" state="rrryyyrrryyy"/>
    <tlsState time="810.00" id="gneJ10" programID="0" phase="0" state="GGgrrrGGgrrr"/>
    <tlsState time="834.00" id="gneJ12" programID="0" phase="1" state="yyyrrryyyrrr"/>
    <tlsState time="837.00" id="gneJ12" programID="0" phase="2" state="rrrGGgrrrGGg"/>
    <tlsState time="843.00" id="gneJ11" programID="0" phase="3" state="rrryyyrrryyy"/>
    <tlsState time="846.00" id="gneJ11" programID="0" phase="0" state="GGgrrrGGgrrr"/>
    <tlsState time="852.00" id="gneJ10" programID="0" phase="1" state="yyyrrryyyrrr"/>
    <tlsState time="855.00" id="gneJ10" programID="0" phase="2" state="rrrGGgrrrGGg"/>
    <tlsState time="879.00" id="gneJ12" programID="0" phase="3" state="rrryyyrrryyy"/>
    <tlsState time="882.00" id="gneJ12" programID="0" phase="0" state="GGgrrrGGgrrr"/>
    <tlsState time="888.00" id="gneJ11" programID="0" phase="1" state="yyyrrryyyrrr"/>
    <tlsState time="891.00" id="gneJ11" programID="0" phase="2" state="rrrGGgrrrGGg"/>
    <tlsState time="897.00" id="gneJ10" programID="0" phase="3" state="rrryyyrrryyy"/>
    <tlsState time="900.00" id="gneJ10" programID="0" phase="0" state="GGgrrrGGgrrr"/>
    <tlsState time="924.00" id="gneJ12" programID="0" phase="1" state="yyyrrryyyrrr"/>
    <tlsState time="927.00" id="gneJ12" programID="0" phase="2" state="rrrGGgrrrGGg"/>
    <tlsState time="933.00" id="gneJ11" programID="0" phase="3" state="rrryyyrrryyy"/>
    <tlsState time="936.00" id="gneJ11" programID="0" phase="0" state="GGgrrrGGgrrr"/>
    <tlsState time="942.00" id="gneJ10" programID="0" phase="1" state="yyyrrryyyrrr"/>
    <tlsState time="945.00" id="gneJ10" programID="0" phase="2" state="rrrGGgrrrGGg"/>
    <tlsState time="969.00" id="gneJ12" programID="0" phase="3" state="rrryyyrrryyy"/>
    <tlsState time="972.00" id="gneJ12" programID="0" phase="0" state="GGgrrrGGgrrr"/>
    <tlsState time="978.00" id="gneJ11" programID="0" phase="1" state="yyyrrryyyrrr"/>
    <tlsState time="981.00" id="gneJ11" programID="0" phase="2" state="rrrGGgrrrGGg"/>
    <tlsState time="987.00" id="gneJ10" programID="0" phase="3" state="rrryyyrrryyy"/>
    <tlsState time="990.00" id="gneJ10" programID="0" phase="0" state="GGgrrrGGgrrr"/>
    <tlsState time="1014.00" id="gneJ12" programID="0" phase="1" state="yyyrrryyyrrr"/>
    <tlsState time="1017.00" id="gneJ12" programID="0" phase="2" state="rrrGGgrrrGGg"/>
    <tlsState time="1023.00" id="gneJ11" programID="0" phase="3" state="rrryyyrrryyy"/>
    <tlsState time="1026.00" id="gneJ11" programID="0" phase="0" state="GGgrrrGGgrrr"/>
    <tlsState time="1032.00" id="gneJ10" programID="0" phase="1" state="yyyrrryyyrrr"/>
    <tlsState time="1035.00" id="gneJ10" programID="0" phase="2" state="rrrGGgrrrGGg"/>
    <tlsState time="1059.00" id="gneJ12" programID="0" phase="3" state="rrryyyrrryyy"/>
    <tlsState time="1062.00" id="gneJ12" programID="0" phase="0" state="GGgrrrGGgrrr"/>
    <tlsState time="1068.00" id="gneJ11" programID="0" phase="1" state="yyyrrryyyrrr"/>
    <tlsState time="1071.00" id="gneJ11" programID="0" phase="2" state="rrrGGgrrrGGg"/>
    <tlsState time="1077.00" id="gneJ10" programID="0" phase="3" state="rrryyyrrryyy"/>
    <tlsState time="1080.00" id="gneJ10" programID="0" phase="0" state="GGgrrrGGgrrr"/>
    <tlsState time="1104.00" id="gneJ12" programID="0" phase="1" state="yyyrrryyyrrr"/>
    <tlsState time="1107.00" id="gneJ12" programID="0" phase="2" state="rrrGGgrrrGGg"/>
    <tlsState time="1113.00" id="gneJ11" programID="0" phase="3" state="rrryyyrrryyy"/>
    <tlsState time="1116.00" id="gneJ11" programID="0" phase="0" state="GGgrrrGGgrrr"/>
    <tlsState time="1122.00" id="gneJ10" programID="0" phase="1" state="yyyrrryyyrrr"/>
    <tlsState time="1125.00" id="gneJ10" programID="0" phase="2" state="rrrGGgrrrGGg"/>
    <tlsState time="1149.00" id="gneJ12" programID="0" phase="3" state="rrryyyrrryyy"/>
    <tlsState time="1152.00" id="gneJ12" programID="0" phase="0" state="GGgrrrGGgrrr"/>
    <tlsState time="1158.00" id="gneJ11" programID="0" phase="1" state="yyyrrryyyrrr"/>
    <tlsState time="1161.00" id="gneJ11" programID="0" phase="2" state="rrrGGgrrrGGg"/>
    <tlsState time="1167.00" id="gneJ10" programID="0" phase="3" state="rrryyyrrryyy"/>
    <tlsState time="1170.00" id="gneJ10" programID="0" phase="0" state="GGgrrrGGgrrr"/>
    <tlsState time="1194.00" id="gneJ12" programID="0" phase="1" state="yyyrrryyyrrr"/>
    <tlsState time="1197.00" id="gneJ12" programID="0" phase="2" state="rrrGGgrrrGGg"/>
    <tlsState time="1203.00" id="gneJ11" programID="0" phase="3" state="rrryyyrrryyy"/>
    <tlsState time="1206.00" id="gneJ11" programID="0" phase="0" state="GGgrrrGGgrrr"/>
    <tlsState time="1212.00" id="gneJ10" programID="0" phase="1" state="yyyrrryyyrrr"/>
    <tlsState time="1215.00" id="gneJ10" programID="0" phase="2" state="rrrGGgrrrGGg"/>
    <tlsState time="1239.00" id="gneJ12" programID="0" phase="3" state="rrryyyrrryyy"/>
    <tlsState time="1242.00" id="gneJ12" programID="0" phase="0" state="GGgrrrGGgrrr"/>
    <tlsState time="1248.00" id="gneJ11" programID="0" phase="1" state="yyyrrryyyrrr"/>
    <tlsState time="1251.00" id="gneJ11" programID="0" phase="2" state="rrrGGgrrrGGg"/>
    <tlsState time="1257.00" id="gneJ10" programID="0" phase="3" state="rrryyyrrryyy"/>
    <tlsState time="1260.00" id="gneJ10" programID="0" phase="0" state="GGgrrrGGgrrr"/>
    <tlsState time="1284.00" id="gneJ12" programID="0" phase="1" state="yyyrrryyyrrr"/>
    <tlsState time="1287.00" id="gneJ12" programID="0" phase="2" state="rrrGGgrrrGGg"/>
    <tlsState time="1293.00" id="gneJ11" programID="0" phase="3" state="rrryyyrrryyy"/>
    <tlsState time="1296.00" id="gneJ11" programID="0" phase="0" state="GGgrrrGGgrrr"/>
    <tlsState time="1302.00" id="gneJ10" programID="0" phase="1" state="yyyrrryyyrrr"/>
    <tlsState time="1305.00" id="gneJ10" programID="0" phase="2" state="rrrGGgrrrGGg"/>
    <tlsState time="1329.00" id="gneJ12" programID="0" phase="3" state="rrryyyrrryyy"/>
    <tlsState time="1332.00" id="gneJ12" programID="0" phase="0" state="GGgrrrGGgrrr"/>
    <tlsState time="1338.00" id="gneJ11" programID="0" phase="1" state="yyyrrryyyrrr"/>
    <tlsState time="1341.00" id="gneJ11" programID="0" phase="2" state="rrrGGgrrrGGg"/>
    <tlsState time="1347.00" id="gneJ10" programID="0" phase="3" state="rrryyyrrryyy"/>
    <tlsState time="1350.00" id="gneJ10" programID="0" phase="0" state="GGgrrrGGgrrr"/>
    <tlsState time="1374.00" id="gneJ12" programID="0" phase="1" state="yyyrrryyyrrr"/>
    <tlsState time="1377.00" id="gneJ12" programID="0" phase="2" state="rrrGGgrrrGGg"/>
    <tlsState time="1383.00" id="gneJ11" programID="0" phase="3" state="rrryyyrrryyy"/>
    <tlsState time="1386.00" id="gneJ11" programID="0" phase="0" state="GGgrrrGGgrrr"/>
    <tlsState time="1391.00" id="gneJ10" programID="online" phase="0" state="rrrrrrrrrggg"/>
    <tlsState time="1419.00" id="gneJ12" programID="0" phase="3" state="rrryyyrrryyy"/>
    <tlsState time="1422.00" id="gneJ12" programID="0" phase="0" state="GGgrrrGGgrrr"/>
    <tlsState time="1428.00" id="gneJ11" programID="0" phase="1" state="yyyrrryyyrrr"/>
    <tlsState time="1431.00" id="gneJ11" programID="0" phase="2" state="rrrGGgrrrGGg"/>
    <tlsState time="1432.00" id="gneJ10" programID="0" phase="2" state="rrrGGgrrrGGg"/>
    <tlsState time="1432.00" id="gneJ11" programID="online" phase="0" state="rrrrrrrrrggg"/>
    <tlsState time="1437.00" id="gneJ10" programID="0" phase="3" state="rrryyyrrryyy"/>
    <tlsState time="1440.00" id="gneJ10" programID="0" phase="0" state="GGgrrrGGgrrr"/>
    <tlsState time="1464.00" id="gneJ12" programID="0" phase="1" state="yyyrrryyyrrr"/>
    <tlsState time="1467.00" id="gneJ12" programID="0" phase="2" state="rrrGGgrrrGGg"/>
    <tlsState time="1482.00" id="gneJ10" programID="0" phase="1" state="yyyrrryyyrrr"/>
    <tlsState time="1485.00" id="gneJ10" programID="0" phase="2" state="rrrGGgrrrGGg"/>
    <tlsState time="1486.00" id="gneJ11" programID="0" phase="0" state="GGgrrrGGgrrr"/>
    <tlsState time="1486.00" id="gneJ12" programID="online" phase="0" state="rrrrrrrrrggg"/>
    <tlsState time="1518.00" id="gneJ11" programID="0" phase="1" state="yyyrrryyyrrr"/>
    <tlsState time="1521.00" id="gneJ11" programID="0" phase="2" state="rrrGGgrrrGGg"/>
    <tlsState time="1524.00" id="gneJ12" programID="0" phase="0" state="GGgrrrGGgrrr"/>
    <tlsState time="1527.00" id="gneJ10" programID="0" phase="3" state="rrryyyrrryyy"/>
    <tlsState time="1530.00" id="gneJ10" programID="0" phase="0" state="GGgrrrGGgrrr"/>
    <tlsState time="1554.00" id="gneJ12" programID="0" phase="1" state="yyyrrryyyrrr"/>
    <tlsState time="1557.00" id="gneJ12" programID="0" phase="2" state="rrrGGgrrrGGg"/>
    <tlsState time="1563.00" id="gneJ11" programID="0" phase="3" state="rrryyyrrryyy"/>
    <tlsState time="1566.00" id="gneJ11" programID="0" phase="0" state="GGgrrrGGgrrr"/>
    <tlsState time="1572.00" id="gneJ10" programID="0" phase="1" state="yyyrrryyyrrr"/>
    <tlsState time="1575.00" id="gneJ10" programID="0" phase="2" state="rrrGGgrrrGGg"/>
    <tlsState time="1599.00" id="gneJ12" programID="0" phase="3" state="rrryyyrrryyy"/>
    <tlsState time="1602.00" id="gneJ12" programID="0" phase="0" state="GGgrrrGGgrrr"/>
    <tlsState time="1608.00" id="gneJ11" programID="0" phase="1" state="yyyrrryyyrrr"/>
    <tlsState time="1611.00" id="gneJ11" programID="0" phase="2" state="rrrGGgrrrGGg"/>
    <tlsState time="1617.00" id="gneJ10" programID="0" phase="3" state="rrryyyrrryyy"/>
    <tlsState time="1620.00" id="gneJ10" programID="0" phase="0" state="GGgrrrGGgrrr"/>
    <tlsState time="1644.00" id="gneJ12" programID="0" phase="1" state="yyyrrryyyrrr"/>
    <tlsState time="1647.00" id="gneJ12" programID="0" phase="2" state="rrrGGgrrrGGg"/>
    <tlsState time="1653.00" id="gneJ11" programID="0" phase="3" state="rrryyyrrryyy"/>
    <tlsState time="1656.00" id="gneJ11" programID="0" phase="0" state="GGgrrrGGgrrr"/>
    <tlsState time="1662.00" id="gneJ10" programID="0" phase="1" state="yyyrrryyyrrr"/>
    <tlsState time="1665.00" id="gneJ10" programID="0" phase="2" state="rrrGGgrrrGGg"/>
    <tlsState time="1689.00" id="gneJ12" programID="0" phase="3" state="rrryyyrrryyy"/>
    <tlsState time="1692.00" id="gneJ12" programID="0" phase="0" state="GGgrrrGGgrrr"/>
    <tlsState time="1698.00" id="gneJ11" programID="0" phase="1" state="yyyrrryyyrrr"/>
    <tlsState time="1701.00" id="gneJ11" programID="0" phase="2" state="rrrGGgrrrGGg"/>
    <tlsState time="1707.00" id="gneJ10" programID="0" phase="3" state="rrryyyrrryyy"/>
    <tlsState time="1710.00" id="gneJ10" programID="0" phase="0" state="GGgrrrGGgrrr"/>
    <tlsState time="1734.00" id="gneJ12" programID="0" phase="1" state="yyyrrryyyrrr"/>
    <tlsState time="1737.00" id="gneJ12" programID="0" phase="2" state="rrrGGgrrrGGg"/>
    <tlsState time="1743.00" id="gneJ11" programID="0" phase="3" state="rrryyyrrryyy"/>
    <tlsState time="1746.00" id="gneJ11" programID="0" phase="0" state="GGgrrrGGgrrr"/>
    <tlsState time="1752.00" id="gneJ10" programID="0" phase="1" state="yyyrrryyyrrr"/>
    <tlsState time="1755.00" id="gneJ10" programID="0" phase="2" state="rrrGGgrrrGGg"/>
    <tlsState time="1779.00" id="gneJ12" programID="0" phase="3" state="rrryyyrrryyy"/>
    <tlsState time="1782.00" id="gneJ12" programID="0" phase="0" state="GGgrrrGGgrrr"/>
    <tlsState time="1788.00" id="gneJ11" programID="0" phase="1" state="yyyrrryyyrrr"/>
    <tlsState time="1791.00" id="gneJ11" programID="0" phase="2" state="rrrGGgrrrGGg"/>
    <tlsState time="1797.00" id="gneJ10" programID="0" phase="3" state="rrryyyrrryyy"/>
    <tlsState time="1800.00" id="gneJ10" programID="0" phase="0" state="GGgrrrGGgrrr"/>
    <tlsState time="1824.00" id="gneJ12" programID="0" phase="1" state="yyyrrryyyrrr"/>
    <tlsState time="1827.00" id="gneJ12" programID="0" phase="2" state="rrrGGgrrrGGg"/>
    <tlsState time="1833.00" id="gneJ11" programID="0" phase="3" state="rrryyyrrryyy"/>
    <tlsState time="1836.00" id="gneJ11" programID="0" phase="0" state="GGgrrrGGgrrr"/>
    <tlsState time="1842.00" id="gneJ10" programID="0" phase="1" state="yyyrrryyyrrr"/>
    <tlsState time="1845.00" id="gneJ10" programID="0" phase="2" state="rrrGGgrrrGGg"/>
    <tlsState time="1869.00" id="gneJ12" programID="0" phase="3" state="rrryyyrrryyy"/>
    <tlsState time="1872.00" id="gneJ12" programID="0" phase="0" state="GGgrrrGGgrrr"/>
    <tlsState time="1878.00" id="gneJ11" programID="0" phase="1" state="yyyrrryyyrrr"/>
    <tlsState time="1881.00" id="gneJ11" programID="0" phase="2" state="rrrGGgrrrGGg"/>
    <tlsState time="1887.00" id="gneJ10" programID="0" phase="3" state="rrryyyrrryyy"/>
    <tlsState time="1890.00" id="gneJ10" programID="0" phase="0" state="GGgrrrGGgrrr"/>
    <tlsState time="1914.00" id="gneJ12" programID="0" phase="1" state="yyyrrryyyrrr"/>
    <tlsState time="1917.00" id="gneJ12" programID="0" phase="2" state="rrrGGgrrrGGg"/>
    <tlsState time="1923.00" id="gneJ11" programID="0" phase="3" state="rrryyyrrryyy"/>
    <tlsState time="1926.00" id="gneJ11" programID="0" phase="0" state="GGgrrrGGgrrr"/>
    <tlsState time="1932.00" id="gneJ10" programID="0" phase="1" state="yyyrrryyyrrr"/>
    <tlsState time="1935.00" id="gneJ10" programID="0" phase="2" state="rrrGGgrrrGGg"/>
    <tlsState time="1959.00" id="gneJ12" programID="0" phase="3" state="rrryyyrrryyy"/>
    <tlsState time="1962.00" id="gneJ12" programID="0" phase="0" state="GGgrrrGGgrrr"/>
    <tlsState time="1968.00" id="gneJ11" programID="0" phase="1" state="yyyrrryyyrrr"/>
    <tlsState time="1971.00" id="gneJ11" programID="0" phase="2" state="rrrGGgrrrGGg"/>
    <tlsState time="1977.00" id="gneJ10" programID="0" phase="3" state="rrryyyrrryyy"/>
    <tlsState time="1980.00" id="gneJ10" programID="0" phase="0" state="GGgrrrGGgrrr"/>
    <tlsState time="2004.00" id="gneJ12" programID="0" phase="1" state="yyyrrryyyrrr"/>
    <tlsState time="2007.00" id="gneJ12" programID="0" phase="2" state="rrrGGgrrrGGg"/>
    <tlsState time="2013.00" id="gneJ11" programID="0" phase="3" state="rrryyyrrryyy"/>
    <tlsState time="2016.00" id="gneJ11" programID="0" phase="0" state="GGgrrrGGgrrr"/>
    <tlsState time="2022.00" id="gneJ10" programID="0" phase="1" state="yyyrrryyyrrr"/>
    <tlsState time="2025.00" id="gneJ10" programID="0" phase="2" state="rrrGGgrrrGGg"/>
    <tlsState time="2049.00" id="gneJ12" programID="0" phase="3" state="rrryyyrrryyy"/>
    <tlsState time="2052.00" id="gneJ12" programID="0" phase="0" state="GGgrrrGGgrrr"/>
    <tlsState time="2058.00" id="gneJ11" programID="0" phase="1" state="yyyrrryyyrrr"/>
    <tlsState time="2061.00" id="gneJ11" programID="0" phase="2" state="rrrGGgrrrGGg"/>
    <tlsState time="2067.00" id="gneJ10" programID="0" phase="3" state="rrryyyrrryyy"/>
    <tlsState time="2070.00" id="gneJ10" programID="0" phase="0" state="GGgrrrGGgrrr"/>
    <tlsState time="2094.00" id="gneJ12" programID="0" phase="1" state="yyyrrryyyrrr"/>
    <tlsState time="2097.00" id="gneJ12" programID="0" phase="2" state="rrrGGgrrrGGg"/>
    <tlsState time="2103.00" id="gneJ11" programID="0" phase="3" state="rrryyyrrryyy"/>
    <tlsState time="2106.00" id="gneJ11" programID="0" phase="0" state="GGgrrrGGgrrr"/>
    <tlsState time="2112.00" id="gneJ10" programID="0" phase="1" state="yyyrrryyyrrr"/>
    <tlsState time="2115.00" id="gneJ10" programID="0" phase="2" state="rrrGGgrrrGGg"/>
    <tlsState time="2139.00" id="gneJ12" programID="0" phase="3" state="rrryyyrrryyy"/>
    <tlsState time="2142.00" id="gneJ12" programID="0" phase="0" state="GGgrrrGGgrrr"/>
    <tlsState time="2148.00" id="gneJ11" programID="0" phase="1" state="yyyrrryyyrrr"/>
    <tlsState time="2151.00" id="gneJ11" programID="0" phase="2" state="rrrGGgrrrGGg"/>
    <tlsState time="2157.00" id="gneJ10" programID="0" phase="3" state="rrryyyrrryyy"/>
    <tlsState time="2160.00" id="gneJ10" programID="0" phase="0" state="GGgrrrGGgrrr"/>
    <tlsState time="2184.00" id="gneJ12" programID="0" phase="1" state="yyyrrryyyrrr"/>
    <tlsState time="2187.00" id="gneJ12" programID="0" phase="2" state="rrrGGgrrrGGg"/>
    <tlsState time="2193.00" id="gneJ11" programID="0" phase="3" state="rrryyyrrryyy"/>
    <tlsState time="2196.00" id="gneJ11" programID="0" phase="0" state="GGgrrrGGgrrr"/>
    <tlsState time="2202.00" id="gneJ10" programID="0" phase="1" state="yyyrrryyyrrr"/>
    <tlsState time="2205.00" id="gneJ10" programID="0" phase="2" state="rrrGGgrrrGGg"/>
    <tlsState time="2229.00" id="gneJ12" programID="0" phase="3" state="rrryyyrrryyy"/>
    <tlsState time="2232.00" id="gneJ12" programID="0" phase="0" state="GGgrrrGGgrrr"/>
    <tlsState time="2238.00" id="gneJ11" programID="0" phase="1" state="yyyrrryyyrrr"/>
    <tlsState time="2241.00" id="gneJ11" programID="0" phase="2" state="rrrGGgrrrGGg"/>
    <tlsState time="2247.00" id="gneJ10" programID="0" phase="3" state="rrryyyrrryyy"/>
    <tlsState time="2250.00" id="gneJ10" programID="0" phase="0" state="GGgrrrGGgrrr"/>
    <tlsState time="2274.00" id="gneJ12" programID="0" phase="1" state="yyyrrryyyrrr"/>
    <tlsState time="2277.00" id="gneJ12" programID="0" phase="2" state="rrrGGgrrrGGg"/>
    <tlsState time="2283.00" id="gneJ11" programID="0" phase="3" state="rrryyyrrryyy"/>
    <tlsState time="2286.00" id="gneJ11" programID="0" phase="0" state="GGgrrrGGgrrr"/>
    <tlsState time="2292.00" id="gneJ10" programID="0" phase="1" state="yyyrrryyyrrr"/>
    <tlsState time="2295.00" id="gneJ10" programID="0" phase="2" state="rrrGGgrrrGGg"/>
    <tlsState time="2319.00" id="gneJ12" programID="0" phase="3" state="rrryyyrrryyy"/>
    <tlsState time="2322.00" id="gneJ12" programID="0" phase="0" state="GGgrrrGGgrrr"/>
    <tlsState time="2328.00" id="gneJ11" programID="0" phase="1" state="yyyrrryyyrrr"/>
    <tlsState time="2331.00" id="gneJ11" programID="0" phase="2" state="rrrGGgrrrGGg"/>
    <tlsState time="2337.00" id="gneJ10" programID="0" phase="3" state="rrryyyrrryyy"/>
    <tlsState time="2340.00" id="gneJ10" programID="0" phase="0" state="GGgrrrGGgrrr"/>
    <tlsState time="2364.00" id="gneJ12" programID="0" phase="1" state="yyyrrryyyrrr"/>
    <tlsState time="2367.00" id="gneJ12" programID="0" phase="2" state="rrrGGgrrrGGg"/>
    <tlsState time="2373.00" id="gneJ11" programID="0" phase="3" state="rrryyyrrryyy"/>
    <tlsState time="2376.00" id="gneJ11" programID="0" phase="0" state="GGgrrrGGgrrr"/>
    <tlsState time="2382.00" id="gneJ10" programID="0" phase="1" state="yyyrrryyyrrr"/>
    <tlsState time="2385.00" id="gneJ10" programID="0" phase="2" state="rrrGGgrrrGGg"/>
    <tlsState time="2409.00" id="gneJ12" programID="0" phase="3" state="rrryyyrrryyy"/>
    <tlsState time="2412.00" id="gneJ12" programID="0" phase="0" state="GGgrrrGGgrrr"/>
    <tlsState time="2418.00" id="gneJ11" programID="0" phase="1" state="yyyrrryyyrrr"/>
    <tlsState time="2421.00" id="gneJ11" programID="0" phase="2" state="rrrGGgrrrGGg"/>
    <tlsState time="2427.00" id="gneJ10" programID="0" phase="3" state="rrryyyrrryyy"/>
    <tlsState time="2430.00" id="gneJ10" programID="0" phase="0" state="GGgrrrGGgrrr"/>
    <tlsState time="2454.00" id="gneJ12" programID="0" phase="1" state="yyyrrryyyrrr"/>
    <tlsState time="2457.00" id="gneJ12" programID="0" phase="2" state="rrrGGgrrrGGg"/>
    <tlsState time="2463.00" id="gneJ11" programID="0" phase="3" state="rrryyyrrryyy"/>
    <tlsState time="2466.00" id="gneJ11" programID="0" phase="0" state="GGgrrrGGgrrr"/>
    <tlsState time="2472.00" id="gneJ10" programID="0" phase="1" state="yyyrrryyyrrr"/>
    <tlsState time="2475.00" id="gneJ10" programID="0" phase="2" state="rrrGGgrrrGGg"/>
    <tlsState time="2499.00" id="gneJ12" programID="0" phase="3" state="rrryyyrrryyy"/>
    <tlsState time="2502.00" id="gneJ12" programID="0" phase="0" state="GGgrrrGGgrrr"/>
    <tlsState time="2508.00" id="gneJ11" programID="0" phase="1" state="yyyrrryyyrrr"/>
    <tlsState time="2511.00" id="gneJ11" programID="0" phase="2" state="rrrGGgrrrGGg"/>
    <tlsState time="2517.00" id="gneJ10" programID="0" phase="3" state="rrryyyrrryyy"/>
    <tlsState time="2520.00" id="gneJ10" programID="0" phase="0" state="GGgrrrGGgrrr"/>
    <tlsState time="2544.00" id="gneJ12" programID="0" phase="1" state="yyyrrryyyrrr"/>
    <tlsState time="2547.00" id="gneJ12" programID="0" phase="2" state="rrrGGgrrrGGg"/>
    <tlsState time="2553.00" id="gneJ11" programID="0" phase="3" state="rrryyyrrryyy"/>
    <tlsState time="2556.00" id="gneJ11" programID="0" phase="0" state="GGgrrrGGgrrr"/>
    <tlsState time="2562.00" id="gneJ10" programID="0" phase="1" state="yyyrrryyyrrr"/>
    <tlsState time="2565.00" id="gneJ10" programID="0" phase="2" state="rrrGGgrrrGGg"/>
    <tlsState time="2589.00" id="gneJ12" programID="0" phase="3" state="rrryyyrrryyy"/>
    <tlsState time="2592.00" id="gneJ12" programID="0" phase="0" state="GGgrrrGGgrrr"/>
    <tlsState time="2598.00" id="gneJ11" programID="0" phase="1" state="yyyrrryyyrrr"/>
    <tlsState time="2601.00" id="gneJ11" programID="0" phase="2" state="rrrGGgrrrGGg"/>
    <tlsState time="2607.00" id="gneJ10" programID="0" phase="3" state="rrryyyrrryyy"/>
    <tlsState time="2610.00" id="gneJ10" programID="0" phase="0" state="GGgrrrGGgrrr"/>
    <tlsState time="2634.00" id="gneJ12" programID="0" phase="1" state="yyyrrryyyrrr"/>
    <tlsState time="2637.00" id="gneJ12" programID="0" phase="2" state="rrrGGgrrrGGg"/>
    <tlsState time="2643.00" id="gneJ11" programID="0" phase="3" state="rrryyyrrryyy"/>
    <tlsState time="2646.00" id="gneJ11" programID="0" phase="0" state="GGgrrrGGgrrr"/>
    <tlsState time="2652.00" id="gneJ10" programID="0" phase="1" state="yyyrrryyyrrr"/>
    <tlsState time="2655.00" id="gneJ10" programID="0" phase="2" state="rrrGGgrrrGGg"/>
    <tlsState time="2679.00" id="gneJ12" programID="0" phase="3" state="rrryyyrrryyy"/>
    <tlsState time="2682.00" id="gneJ12" programID="0" phase="0" state="GGgrrrGGgrrr"/>
    <tlsState time="2688.00" id="gneJ11" programID="0" phase="1" state="yyyrrryyyrrr"/>
    <tlsState time="2691.00" id="gneJ11" programID="0" phase="2" state="rrrGGgrrrGGg"/>
    <tlsState time="2697.00" id="gneJ10" programID="0" phase="3" state="rrryyyrrryyy"/>
    <tlsState time="2700.00" id="gneJ10" programID="0" phase="0" state="GGgrrrGGgrrr"/>
    <tlsState time="2724.00" id="gneJ12" programID="0" phase="1" state="yyyrrryyyrrr"/>
    <tlsState time="2727.00" id="gneJ12" programID="0" phase="2" state="rrrGGgrrrGGg"/>
    <tlsState time="2733.00" id="gneJ11" programID="0" phase="3" state="rrryyyrrryyy"/>
    <tlsState time="2736.00" id="gneJ11" programID="0" phase="0" state="GGgrrrGGgrrr"/>
    <tlsState time="2742.00" id="gneJ10" programID="0" phase="1" state="yyyrrryyyrrr"/>
    <tlsState time="2745.00" id="gneJ10" programID="0" phase="2" state="rrrGGgrrrGGg"/>
    <tlsState time="2769.00" id="gneJ12" programID="0" phase="3" state="rrryyyrrryyy"/>
    <tlsState time="2772.00" id="gneJ12" programID="0" phase="0" state="GGgrrrGGgrrr"/>
    <tlsState time="2778.00" id="gneJ11" programID="0" phase="1" state="yyyrrryyyrrr"/>
    <tlsState time="2781.00" id="gneJ11" programID="0" phase="2" state="rrrGGgrrrGGg"/>
    <tlsState time="2787.00" id="gneJ10" programID="0" phase="3" state="rrryyyrrryyy"/>
    <tlsState time="2790.00" id="gneJ10" programID="0" phase="0" state="GGgrrrGGgrrr"/>
    <tlsState time="2814.00" id="gneJ12" programID="0" phase="1" state="yyyrrryyyrrr"/>
    <tlsState time="2817.00" id="gneJ12" programID="0" phase="2" state="rrrGGgrrrGGg"/>
    <tlsState time="2823.00" id="gneJ11" programID="0" phase="3" state="rrryyyrrryyy"/>
    <tlsState time="2826.00" id="gneJ11" programID="0" phase="0" state="GGgrrrGGgrrr"/>
    <tlsState time="2832.00" id="gneJ10" programID="0" phase="1" state="yyyrrryyyrrr"/>
    <tlsState time="2835.00" id="gneJ10" programID="0" phase="2" state="rrrGGgrrrGGg"/>
    <tlsState time="2859.00" id="gneJ12" programID="0" phase="3" state="rrryyyrrryyy"/>
    <tlsState time="2862.00" id="gneJ12" programID="0" phase="0" state="GGgrrrGGgrrr"/>
    <tlsState time="2868.00" id="gneJ11" programID="0" phase="1" state="yyyrrryyyrrr"/>
    <tlsState time="2871.00" id="gneJ11" programID="0" phase="2" state="rrrGGgrrrGGg"/>
    <tlsState time="2877.00" id="gneJ10" programID="0" phase="3" state="rrryyyrrryyy"/>
    <tlsState time="2880.00" id="gneJ10" programID="0" phase="0" state="GGgrrrGGgrrr"/>
    <tlsState time="2904.00" id="gneJ12" programID="0" phase="1" state="yyyrrryyyrrr"/>
    <tlsState time="2907.00" id="gneJ12" programID="0" phase="2" state="rrrGGgrrrGGg"/>
    <tlsState time="2913.00" id="gneJ11" programID="0" phase="3" state="rrryyyrrryyy"/>
    <tlsState time="2916.00" id="gneJ11" programID="0" phase="0" state="GGgrrrGGgrrr"/>
    <tlsState time="2922.00" id="gneJ10" programID="0" phase="1" state="yyyrrryyyrrr"/>
    <tlsState time="2925.00" id="gneJ10" programID="0" phase="2" state="rrrGGgrrrGGg"/>
    <tlsState time="2949.00" id="gneJ12" programID="0" phase="3" state="rrryyyrrryyy"/>
    <tlsState time="2952.00" id="gneJ12" programID="0" phase="0" state="GGgrrrGGgrrr"/>
    <tlsState time="2958.00" id="gneJ11" programID="0" phase="1" state="yyyrrryyyrrr"/>
    <tlsState time="2961.00" id="gneJ11" programID="0" phase="2" state="rrrGGgrrrGGg"/>
    <tlsState time="2967.00" id="gneJ10" programID="0" phase="3" state="rrryyyrrryyy"/>
    <tlsState time="2970.00" id="gneJ10" programID="0" phase="0" state="GGgrrrGGgrrr"/>
    <tlsState time="2994.00" id="gneJ12" programID="0" phase="1" state="yyyrrryyyrrr"/>
    <tlsState time="2997.00" id="gneJ12" programID="0" phase="2" state="rrrGGgrrrGGg"/>
    <tlsState time="3003.00" id="gneJ11" programID="0" phase="3" state="rrryyyrrryyy"/>
    <tlsState time="3006.00" id="gneJ11" programID="0" phase="0" state="GGgrrrGGgrrr"/>
    <tlsState time="3012.00" id="gneJ10" programID="0" phase="1" state="yyyrrryyyrrr"/>
    <tlsState time="3015.00" id="gneJ10" programID="0" phase="2" state="rrrGGgrrrGGg"/>
    <tlsState time="3039.00" id="gneJ12" programID="0" phase="3" state="rrryyyrrryyy"/>
    <tlsState time="3042.00" id="gneJ12" programID="0" phase="0" state="GGgrrrGGgrrr"/>
    <tlsState time="3048.00" id="gneJ11" programID="0" phase="1" state="yyyrrryyyrrr"/>
    <tlsState time="3051.00" id="gneJ11" programID="0" phase="2" state="rrrGGgrrrGGg"/>
    <tlsState time="3057.00" id="gneJ10" programID="0" phase="3" state="rrryyyrrryyy"/>
    <tlsState time="3060.00" id="gneJ10" programID="0" phase="0" state="GGgrrrGGgrrr"/>
    <tlsState time="3084.00" id="gneJ12" programID="0" phase="1" state="yyyrrryyyrrr"/>
    <tlsState time="3087.00" id="gneJ12" programID="0" phase="2" state="rrrGGgrrrGGg"/>
    <tlsState time="3093.00" id="gneJ11" programID="0" phase="3" state="rrryyyrrryyy"/>
    <tlsState time="3096.00" id="gneJ11" programID="0" phase="0" state="GGgrrrGGgrrr"/>
    <tlsState time="3102.00" id="gneJ10" programID="0" phase="1" state="yyyrrryyyrrr"/>
    <tlsState time="3105.00" id="gneJ10" programID="0" phase="2" state="rrrGGgrrrGGg"/>
    <tlsState time="3129.00" id="gneJ12" programID="0" phase="3" state="rrryyyrrryyy"/>
    <tlsState time="3132.00" id="gneJ12" programID="0" phase="0" state="GGgrrrGGgrrr"/>
    <tlsState time="3138.00" id="gneJ11" programID="0" phase="1" state="yyyrrryyyrrr"/>
    <tlsState time="3141.00" id="gneJ11" programID="0" phase="2" state="rrrGGgrrrGGg"/>
    <tlsState time="3147.00" id="gneJ10" programID="0" phase="3" state="rrryyyrrryyy"/>
    <tlsState time="3150.00" id="gneJ10" programID="0" phase="0" state="GGgrrrGGgrrr"/>
    <tlsState time="3174.00" id="gneJ12" programID="0" phase="1" state="yyyrrryyyrrr"/>
    <tlsState time="3177.00" id="gneJ12" programID="0" phase="2" state="rrrGGgrrrGGg"/>
    <tlsState time="3183.00" id="gneJ11" programID="0" phase="3" state="rrryyyrrryyy"/>
    <tlsState time="3186.00" id="gneJ11" programID="0" phase="0" state="GGgrrrGGgrrr"/>
    <tlsState time="3192.00" id="gneJ10" programID="0" phase="1" state="yyyrrryyyrrr"/>
    <tlsState time="3195.00" id="gneJ10" programID="0" phase="2" state="rrrGGgrrrGGg"/>
    <tlsState time="3219.00" id="gneJ12" programID="0" phase="3" state="rrryyyrrryyy"/>
    <tlsState time="3222.00" id="gneJ12" programID="0" phase="0" state="GGgrrrGGgrrr"/>
    <tlsState time="3228.00" id="gneJ11" programID="0" phase="1" state="yyyrrryyyrrr"/>
    <tlsState time="3231.00" id="gneJ11" programID="0" phase="2" state="rrrGGgrrrGGg"/>
    <tlsState time="3237.00" id="gneJ10" programID="0" phase="3" state="rrryyyrrryyy"/>
    <tlsState time="3240.00" id="gneJ10" programID="0" phase="0" state="GGgrrrGGgrrr"/>
    <tlsState time="3264.00" id="gneJ12" programID="0" phase="1" state="yyyrrryyyrrr"/>
    <tlsState time="3267.00" id="gneJ12" programID="0" phase="2" state="rrrGGgrrrGGg"/>
    <tlsState time="3273.00" id="gneJ11" programID="0" phase="3" state="rrryyyrrryyy"/>
    <tlsState time="3276.00" id="gneJ11" programID="0" phase="0" state="GGgrrrGGgrrr"/>
    <tlsState time="3282.00" id="gneJ10" programID="0" phase="1" state="yyyrrryyyrrr"/>
    <tlsState time="3285.00" id="gneJ10" programID="0" phase="2" state="rrrGGgrrrGGg"/>
    <tlsState time="3309.00" id="gneJ12" programID="0" phase="3" state="rrryyyrrryyy"/>
    <tlsState time="3312.00" id="gneJ12" programID="0" phase="0" state="GGgrrrGGgrrr"/>
    <tlsState time="3318.00" id="gneJ11" programID="0" phase="1" state="yyyrrryyyrrr"/>
    <tlsState time="3321.00" id="gneJ11" programID="0" phase="2" state="rrrGGgrrrGGg"/>
    <tlsState time="3327.00" id="gneJ10" programID="0" phase="3" state="rrryyyrrryyy"/>
    <tlsState time="3330.00" id="gneJ10" programID="0" phase="0" state="GGgrrrGGgrrr"/>
    <tlsState time="3354.00" id="gneJ12" programID="0" phase="1" state="yyyrrryyyrrr"/>
    <tlsState time="3357.00" id="gneJ12" programID="0" phase="2" state="rrrGGgrrrGGg"/>
    <tlsState time="3363.00" id="gneJ11" programID="0" phase="3" state="rrryyyrrryyy"/>
    <tlsState time="3366.00" id="gneJ11" programID="0" phase="0" state="GGgrrrGGgrrr"/>
    <tlsState time="3372.00" id="gneJ10" programID="0" phase="1" state="yyyrrryyyrrr"/>
    <tlsState time="3375.00" id="gneJ10" programID="0" phase="2" state="rrrGGgrrrGGg"/>
    <tlsState time="3399.00" id="gneJ12" programID="0" phase="3" state="rrryyyrrryyy"/>
    <tlsState time="3402.00" id="gneJ12" programID="0" phase="0" state="GGgrrrGGgrrr"/>
    <tlsState time="3408.00" id="gneJ11" programID="0" phase="1" state="yyyrrryyyrrr"/>
    <tlsState time="3411.00" id="gneJ11" programID="0" phase="2" state="rrrGGgrrrGGg"/>
    <tlsState time="3417.00" id="gneJ10" programID="0" phase="3" state="rrryyyrrryyy"/>
    <tlsState time="3420.00" id="gneJ10" programID="0" phase="0" state="GGgrrrGGgrrr"/>
    <tlsState time="3444.00" id="gneJ12" programID="0" phase="1" state="yyyrrryyyrrr"/>
    <tlsState time="3447.00" id="gneJ12" programID="0" phase="2" state="rrrGGgrrrGGg"/>
    <tlsState time="3453.00" id="gneJ11" programID="0" phase="3" state="rrryyyrrryyy"/>
    <tlsState time="3456.00" id="gneJ11" programID="0" phase="0" state="GGgrrrGGgrrr"/>
    <tlsState time="3462.00" id="gneJ10" programID="0" phase="1" state="yyyrrryyyrrr"/>
    <tlsState time="3465.00" id="gneJ10" programID="0" phase="2" state="rrrGGgrrrGGg"/>
    <tlsState time="3489.00" id="gneJ12" programID="0" phase="3" state="rrryyyrrryyy"/>
    <tlsState time="3492.00" id="gneJ12" programID="0" phase="0" state="GGgrrrGGgrrr"/>
    <tlsState time="3498.00" id="gneJ11" programID="0" phase="1" state="yyyrrryyyrrr"/>
    <tlsState time="3501.00" id="gneJ11" programID="0" phase="2" state="rrrGGgrrrGGg"/>
    <tlsState time="3507.00" id="gneJ10" programID="0" phase="3" state="rrryyyrrryyy"/>
    <tlsState time="3510.00" id="gneJ10" programID="0" phase="0" state="GGgrrrGGgrrr"/>
    <tlsState time="3534.00" id="gneJ12" programID="0" phase="1" state="yyyrrryyyrrr"/>
    <tlsState time="3537.00" id="gneJ12" programID="0" phase="2" state="rrrGGgrrrGGg"/>
    <tlsState time="3543.00" id="gneJ11" programID="0" phase="3" state="rrryyyrrryyy"/>
    <tlsState time="3546.00" id="gneJ11" programID="0" phase="0" state="GGgrrrGGgrrr"/>
    <tlsState time="3552.00" id="gneJ10" programID="0" phase="1" state="yyyrrryyyrrr"/>
    <tlsState time="3555.00" id="gneJ10" programID="0" phase="2" state="rrrGGgrrrGGg"/>
    <tlsState time="3579.00" id="gneJ12" programID="0" phase="3" state="rrryyyrrryyy"/>
    <tlsState time="3582.00" id="gneJ12" programID="0" phase="0" state="GGgrrrGGgrrr"/>
    <tlsState time="3588.00" id="gneJ11" programID="0" phase="1" state="yyyrrryyyrrr"/>
    <tlsState time="3591.00" id="gneJ11" programID="0" phase="2" state="rrrGGgrrrGGg"/>
    <tlsState time="3597.00" id="gneJ10" programID="0" phase="3" state="rrryyyrrryyy"/>
</tlsStates>
